LICENSE
README.md
setup.cfg
setup.py
abase/__init__.py
abase/__main__.py
appiumbase/__init__.py
appiumbase/__main__.py
appiumbase/__version__.py
appiumbase.egg-info/PKG-INFO
appiumbase.egg-info/SOURCES.txt
appiumbase.egg-info/dependency_links.txt
appiumbase.egg-info/entry_points.txt
appiumbase.egg-info/requires.txt
appiumbase.egg-info/top_level.txt
appiumbase/common/__init__.py
appiumbase/common/exceptions.py
appiumbase/config/__init__.py
appiumbase/config/settings.py
appiumbase/console_scripts/__init__.py
appiumbase/console_scripts/ab_mkdir.py
appiumbase/console_scripts/run.py
appiumbase/core/__init__.py
appiumbase/core/appium_launcher.py
appiumbase/core/capabilities_parser.py
appiumbase/fixtures/__init__.py
appiumbase/fixtures/base_case.py
appiumbase/fixtures/constants.py
appiumbase/fixtures/page_actions.py
appiumbase/fixtures/page_utils.py
appiumbase/fixtures/shared_utils.py
appiumbase/plugins/__init__.py
appiumbase/plugins/pytest_plugin.py